{
  "db_name": "PostgreSQL",
  "query": "SELECT id, chat_id, user_id, estimated_response_at, message, response, status AS \"status: _\", created_at, updated_at\n            FROM chat_messages\n            WHERE chat_id = $1\n            ORDER BY created_at ASC",
  "describe": {
    "columns": [
      {
        "ordinal": 0,
        "name": "id",
        "type_info": "Uuid"
      },
      {
        "ordinal": 1,
        "name": "chat_id",
        "type_info": "Uuid"
      },
      {
        "ordinal": 2,
        "name": "user_id",
        "type_info": "Uuid"
      },
      {
        "ordinal": 3,
        "name": "estimated_response_at",
        "type_info": "Timestamptz"
      },
      {
        "ordinal": 4,
        "name": "message",
        "type_info": "Text"
      },
      {
        "ordinal": 5,
        "name": "response",
        "type_info": "Text"
      },
      {
        "ordinal": 6,
        "name": "status: _",
        "type_info": {
          "Custom": {
            "name": "chat_message_statuses",
            "kind": {
              "Enum": [
                "answered",
                "asked"
              ]
            }
          }
        }
      },
      {
        "ordinal": 7,
        "name": "created_at",
        "type_info": "Timestamptz"
      },
      {
        "ordinal": 8,
        "name": "updated_at",
        "type_info": "Timestamptz"
      }
    ],
    "parameters": {
      "Left": [
        "Uuid"
      ]
    },
    "nullable": [
      false,
      false,
      false,
      false,
      false,
      true,
      false,
      false,
      false
    ]
  },
  "hash": "75f772a7791d7ab0daaff4efdd8f2eb747f7dcd14224a828065fc2ede9c172b4"
}
