{
  "db_name": "PostgreSQL",
  "query": "SELECT id, is_visible, priority, prompt, created_at, updated_at\n            FROM example_prompts\n            WHERE is_visible = $1\n            ORDER BY priority DESC",
  "describe": {
    "columns": [
      {
        "ordinal": 0,
        "name": "id",
        "type_info": "Uuid"
      },
      {
        "ordinal": 1,
        "name": "is_visible",
        "type_info": "Bool"
      },
      {
        "ordinal": 2,
        "name": "priority",
        "type_info": "Int4"
      },
      {
        "ordinal": 3,
        "name": "prompt",
        "type_info": "Text"
      },
      {
        "ordinal": 4,
        "name": "created_at",
        "type_info": "Timestamptz"
      },
      {
        "ordinal": 5,
        "name": "updated_at",
        "type_info": "Timestamptz"
      }
    ],
    "parameters": {
      "Left": [
        "Bool"
      ]
    },
    "nullable": [
      false,
      false,
      false,
      false,
      false,
      false
    ]
  },
  "hash": "008f5ea2ef791bfb102040ab1d92a516caa3fcb8381076717879cdee175ad5c8"
}
