{
  "db_name": "PostgreSQL",
  "query": "INSERT INTO chat_message_pictures\n            (chat_message_id, file_name)\n            VALUES ($1, $2)\n            RETURNING id, chat_message_id, file_name, created_at, updated_at",
  "describe": {
    "columns": [
      {
        "ordinal": 0,
        "name": "id",
        "type_info": "Uuid"
      },
      {
        "ordinal": 1,
        "name": "chat_message_id",
        "type_info": "Uuid"
      },
      {
        "ordinal": 2,
        "name": "file_name",
        "type_info": "Varchar"
      },
      {
        "ordinal": 3,
        "name": "created_at",
        "type_info": "Timestamptz"
      },
      {
        "ordinal": 4,
        "name": "updated_at",
        "type_info": "Timestamptz"
      }
    ],
    "parameters": {
      "Left": [
        "Uuid",
        "Varchar"
      ]
    },
    "nullable": [
      false,
      false,
      false,
      false,
      false
    ]
  },
  "hash": "6c11362e1070cf0f0760622b37257a931d1e7d1fe8f5effe39e93569da2cd96c"
}
